Workbook
Name NativeTimeline_Date: #N/A
Name Slicer_Category: #N/A
Name Slicer_Membership_Tier: #N/A
Name Slicer_Region: #N/A

Sheet Dashboard
D1: Status | E1: CRITICAL DELAY
A3: Row Labels | B3: Sum of Total Profit | D3: Row Labels | E3: Count of OrderID
A4: Electronics | B4: 2649.53 | D4: South | E4: 2
A5: Furniture | B5: 2439.94 | D5: Grand Total | E5: 2
A6: Home Decor | B6: 150
A7: (blank)
A8: Grand Total | B8: 5239.47
A10: Row Labels | B10: Sum of Total Revenue
A11: Bronze | B11: 1004.97
A12: Gold | B12: 3039.69
A13: Silver | B13: 3924.81
A14: (blank)
A15: Grand Total | B15: 7969.47

Sheet Raw_orders
A1: OrderID | B1: Date | C1: Cust_ID | D1: Prod_ID | E1: Qty | F1: Ship_Date | G1: Region | H1: Promo_Code | I1: Product Name | J1: Category | K1: Unit Cost | L1: Unit Price | M1: Customer Name | N1: Membership Tier | O1: Total Revenue | P1: Total Profit | Q1: Days to Ship | R1: Status | S1: Promo Valid?
A2: ORD-24-1001 | B2: 45294 | C2: C-001 | D2: P-500 | E2: 5 | F2: 45296 | G2: North | H2: WELCOME10 | I2: =_xlfn.XLOOKUP(D2,Product_Master!A:A,Product_Master!B:B,"Unknown Item") -> Wireless Mouse X1 | J2: =_xlfn.XLOOKUP(D2,Product_Master!A:A,Product_Master!C:C,"Unknown Item") -> Electronics | K2: =_xlfn.XLOOKUP(D2,Product_Master!A:A,Product_Master!D:D,"Unknown Item") -> 12.5 | L2: =_xlfn.XLOOKUP(D2,Product_Master!A:A,Product_Master!E:E,"Unknown Item") -> 39.99 | M2: =_xlfn.XLOOKUP(C2,Customer_database!A:A,Customer_database!E:E,"Unknown Customer") -> John Smith | N2: =_xlfn.XLOOKUP(C2,Customer_database!A:A,Customer_database!D:D,"Unknown") -> Gold | O2: =E2*L2 -> 199.95 | P2: =(L2-K2)*E2 -> 137.45 | Q2: =F2-B2 -> 2 | R2: =IF(AND(Q2>5,OR(G2="North",G2="South")),"CRITICAL DELAY", IF(Q2>5,"Late","On Time")) -> On Time | S2: =OR(H2="WELCOME10",H2="FREESHIP") -> TRUE
A3: ORD-24-1002 | B3: 45295 | C3: C-003 | D3: P-502 | E3: 1 | F3: 45299 | G3: West | I3: =_xlfn.XLOOKUP(D3,Product_Master!A:A,Product_Master!B:B,"Unknown Item") -> Ergo Office Chair | J3: =_xlfn.XLOOKUP(D3,Product_Master!A:A,Product_Master!C:C,"Unknown Item") -> Furniture | K3: =_xlfn.XLOOKUP(D3,Product_Master!A:A,Product_Master!D:D,"Unknown Item") -> 85 | L3: =_xlfn.XLOOKUP(D3,Product_Master!A:A,Product_Master!E:E,"Unknown Item") -> 249.99 | M3: =_xlfn.XLOOKUP(C3,Customer_database!A:A,Customer_database!E:E,"Unknown Customer") -> Emily Blunt | N3: =_xlfn.XLOOKUP(C3,Customer_database!A:A,Customer_database!D:D,"Unknown") -> Bronze | O3: =E3*L3 -> 249.99 | P3: =(L3-K3)*E3 -> 164.99 | Q3: =F3-B3 -> 4 | R3: =IF(AND(Q3>5,OR(G3="North",G3="South")),"CRITICAL DELAY", IF(Q3>5,"Late","On Time")) -> On Time | S3: =OR(H3="WELCOME10",H3="FREESHIP") -> FALSE
A4: ORD-24-1003 | B4: 45297 | C4: C-002 | D4: P-501 | E4: 10 | F4: 45305 | G4: East | H4: BULK25 | I4: =_xlfn.XLOOKUP(D4,Product_Master!A:A,Product_Master!B:B,"Unknown Item") -> Mech Keyboard RGB | J4: =_xlfn.XLOOKUP(D4,Product_Master!A:A,Product_Master!C:C,"Unknown Item") -> Electronics | K4: =_xlfn.XLOOKUP(D4,Product_Master!A:A,Product_Master!D:D,"Unknown Item") -> 45 | L4: =_xlfn.XLOOKUP(D4,Product_Master!A:A,Product_Master!E:E,"Unknown Item") -> 129.99 | M4: =_xlfn.XLOOKUP(C4,Customer_database!A:A,Customer_database!E:E,"Unknown Customer") -> Sarah Connor | N4: =_xlfn.XLOOKUP(C4,Customer_database!A:A,Customer_database!D:D,"Unknown") -> Silver | O4: =E4*L4 -> 1299.9 | P4: =(L4-K4)*E4 -> 849.9 | Q4: =F4-B4 -> 8 | R4: =IF(AND(Q4>5,OR(G4="North",G4="South")),"CRITICAL DELAY", IF(Q4>5,"Late","On Time")) -> Late | S4: =OR(H4="WELCOME10",H4="FREESHIP") -> FALSE
A5: ORD-24-1004 | B5: 45299 | C5: C-005 | D5: P-505 | E5: 2 | F5: 45300 | G5: North | I5: =_xlfn.XLOOKUP(D5,Product_Master!A:A,Product_Master!B:B,"Unknown Item") -> Dual Monitor Arm | J5: =_xlfn.XLOOKUP(D5,Product_Master!A:A,Product_Master!C:C,"Unknown Item") -> Electronics | K5: =_xlfn.XLOOKUP(D5,Product_Master!A:A,Product_Master!D:D,"Unknown Item") -> 25 | L5: =_xlfn.XLOOKUP(D5,Product_Master!A:A,Product_Master!E:E,"Unknown Item") -> 75 | M5: =_xlfn.XLOOKUP(C5,Customer_database!A:A,Customer_database!E:E,"Unknown Customer") -> Dwight Schrute | N5: =_xlfn.XLOOKUP(C5,Customer_database!A:A,Customer_database!D:D,"Unknown") -> Silver | O5: =E5*L5 -> 150 | P5: =(L5-K5)*E5 -> 100 | Q5: =F5-B5 -> 1 | R5: =IF(AND(Q5>5,OR(G5="North",G5="South")),"CRITICAL DELAY", IF(Q5>5,"Late","On Time")) -> On Time | S5: =OR(H5="WELCOME10",H5="FREESHIP") -> FALSE
A6: ORD-24-1005 | B6: 45301 | C6: C-001 | D6: P-500 | E6: 1 | F6: 45303 | G6: North | H6: FREESHIP | I6: =_xlfn.XLOOKUP(D6,Product_Master!A:A,Product_Master!B:B,"Unknown Item") -> Wireless Mouse X1 | J6: =_xlfn.XLOOKUP(D6,Product_Master!A:A,Product_Master!C:C,"Unknown Item") -> Electronics | K6: =_xlfn.XLOOKUP(D6,Product_Master!A:A,Product_Master!D:D,"Unknown Item") -> 12.5 | L6: =_xlfn.XLOOKUP(D6,Product_Master!A:A,Product_Master!E:E,"Unknown Item") -> 39.99 | M6: =_xlfn.XLOOKUP(C6,Customer_database!A:A,Customer_database!E:E,"Unknown Customer") -> John Smith | N6: =_xlfn.XLOOKUP(C6,Customer_database!A:A,Customer_database!D:D,"Unknown") -> Gold | O6: =E6*L6 -> 39.99 | P6: =(L6-K6)*E6 -> 27.49 | Q6: =F6-B6 -> 2 | R6: =IF(AND(Q6>5,OR(G6="North",G6="South")),"CRITICAL DELAY", IF(Q6>5,"Late","On Time")) -> On Time | S6: =OR(H6="WELCOME10",H6="FREESHIP") -> TRUE
A7: ORD-24-1006 | B7: 45303 | C7: C-004 | D7: P-503 | E7: 3 | F7: 45310 | G7: South | H7: WELCOME10 | I7: =_xlfn.XLOOKUP(D7,Product_Master!A:A,Product_Master!B:B,"Unknown Item") -> Oak Standing Desk | J7: =_xlfn.XLOOKUP(D7,Product_Master!A:A,Product_Master!C:C,"Unknown Item") -> Furniture | K7: =_xlfn.XLOOKUP(D7,Product_Master!A:A,Product_Master!D:D,"Unknown Item") -> 160 | L7: =_xlfn.XLOOKUP(D7,Product_Master!A:A,Product_Master!E:E,"Unknown Item") -> 450 | M7: =_xlfn.XLOOKUP(C7,Customer_database!A:A,Customer_database!E:E,"Unknown Customer") -> Michael Scott | N7: =_xlfn.XLOOKUP(C7,Customer_database!A:A,Customer_database!D:D,"Unknown") -> Gold | O7: =E7*L7 -> 1350 | P7: =(L7-K7)*E7 -> 870 | Q7: =F7-B7 -> 7 | R7: =IF(AND(Q7>5,OR(G7="North",G7="South")),"CRITICAL DELAY", IF(Q7>5,"Late","On Time")) -> CRITICAL DELAY | S7: =OR(H7="WELCOME10",H7="FREESHIP") -> TRUE
A8: ORD-24-1007 | B8: 45306 | C8: C-006 | D8: P-504 | E8: 4 | F8: 45313 | G8: West | I8: =_xlfn.XLOOKUP(D8,Product_Master!A:A,Product_Master!B:B,"Unknown Item") -> Smart LED Lamp | J8: =_xlfn.XLOOKUP(D8,Product_Master!A:A,Product_Master!C:C,"Unknown Item") -> Home Decor | K8: =_xlfn.XLOOKUP(D8,Product_Master!A:A,Product_Master!D:D,"Unknown Item") -> 15 | L8: =_xlfn.XLOOKUP(D8,Product_Master!A:A,Product_Master!E:E,"Unknown Item") -> 45 | M8: =_xlfn.XLOOKUP(C8,Customer_database!A:A,Customer_database!E:E,"Unknown Customer") -> Jim Halpert | N8: =_xlfn.XLOOKUP(C8,Customer_database!A:A,Customer_database!D:D,"Unknown") -> Bronze | O8: =E8*L8 -> 180 | P8: =(L8-K8)*E8 -> 120 | Q8: =F8-B8 -> 7 | R8: =IF(AND(Q8>5,OR(G8="North",G8="South")),"CRITICAL DELAY", IF(Q8>5,"Late","On Time")) -> Late | S8: =OR(H8="WELCOME10",H8="FREESHIP") -> FALSE
A9: ORD-24-1008 | B9: 45307 | C9: C-002 | D9: P-501 | E9: 6 | F9: 45309 | G9: East | I9: =_xlfn.XLOOKUP(D9,Product_Master!A:A,Product_Master!B:B,"Unknown Item") -> Mech Keyboard RGB | J9: =_xlfn.XLOOKUP(D9,Product_Master!A:A,Product_Master!C:C,"Unknown Item") -> Electronics | K9: =_xlfn.XLOOKUP(D9,Product_Master!A:A,Product_Master!D:D,"Unknown Item") -> 45 | L9: =_xlfn.XLOOKUP(D9,Product_Master!A:A,Product_Master!E:E,"Unknown Item") -> 129.99 | M9: =_xlfn.XLOOKUP(C9,Customer_database!A:A,Customer_database!E:E,"Unknown Customer") -> Sarah Connor | N9: =_xlfn.XLOOKUP(C9,Customer_database!A:A,Customer_database!D:D,"Unknown") -> Silver | O9: =E9*L9 -> 779.94 | P9: =(L9-K9)*E9 -> 509.94 | Q9: =F9-B9 -> 2 | R9: =IF(AND(Q9>5,OR(G9="North",G9="South")),"CRITICAL DELAY", IF(Q9>5,"Late","On Time")) -> On Time | S9: =OR(H9="WELCOME10",H9="FREESHIP") -> FALSE
A10: ORD-24-1009 | B10: 45309 | C10: C-008 | D10: P-502 | E10: 2 | F10: 45320 | G10: South | H10: LATE_SORRY | I10: =_xlfn.XLOOKUP(D10,Product_Master!A:A,Product_Master!B:B,"Unknown Item") -> Ergo Office Chair | J10: =_xlfn.XLOOKUP(D10,Product_Master!A:A,Product_Master!C:C,"Unknown Item") -> Furniture | K10: =_xlfn.XLOOKUP(D10,Product_Master!A:A,Product_Master!D:D,"Unknown Item") -> 85 | L10: =_xlfn.XLOOKUP(D10,Product_Master!A:A,Product_Master!E:E,"Unknown Item") -> 249.99 | M10: =_xlfn.XLOOKUP(C10,Customer_database!A:A,Customer_database!E:E,"Unknown Customer") -> Ryan Howard | N10: =_xlfn.XLOOKUP(C10,Customer_database!A:A,Customer_database!D:D,"Unknown") -> Bronze | O10: =E10*L10 -> 499.98 | P10: =(L10-K10)*E10 -> 329.98 | Q10: =F10-B10 -> 11 | R10: =IF(AND(Q10>5,OR(G10="North",G10="South")),"CRITICAL DELAY", IF(Q10>5,"Late","On Time")) -> CRITICAL DELAY | S10: =OR(H10="WELCOME10",H10="FREESHIP") -> FALSE
A11: ORD-24-1010 | B11: 45311 | C11: C-003 | D11: P-505 | E11: 1 | F11: 45312 | G11: West | I11: =_xlfn.XLOOKUP(D11,Product_Master!A:A,Product_Master!B:B,"Unknown Item") -> Dual Monitor Arm | J11: =_xlfn.XLOOKUP(D11,Product_Master!A:A,Product_Master!C:C,"Unknown Item") -> Electronics | K11: =_xlfn.XLOOKUP(D11,Product_Master!A:A,Product_Master!D:D,"Unknown Item") -> 25 | L11: =_xlfn.XLOOKUP(D11,Product_Master!A:A,Product_Master!E:E,"Unknown Item") -> 75 | M11: =_xlfn.XLOOKUP(C11,Customer_database!A:A,Customer_database!E:E,"Unknown Customer") -> Emily Blunt | N11: =_xlfn.XLOOKUP(C11,Customer_database!A:A,Customer_database!D:D,"Unknown") -> Bronze | O11: =E11*L11 -> 75 | P11: =(L11-K11)*E11 -> 50 | Q11: =F11-B11 -> 1 | R11: =IF(AND(Q11>5,OR(G11="North",G11="South")),"CRITICAL DELAY", IF(Q11>5,"Late","On Time")) -> On Time | S11: =OR(H11="WELCOME10",H11="FREESHIP") -> FALSE
A12: ORD-24-1011 | B12: 45313 | C12: C-009 | D12: P-500 | E12: 20 | F12: 45314 | G12: North | H12: BULK_VIP | I12: =_xlfn.XLOOKUP(D12,Product_Master!A:A,Product_Master!B:B,"Unknown Item") -> Wireless Mouse X1 | J12: =_xlfn.XLOOKUP(D12,Product_Master!A:A,Product_Master!C:C,"Unknown Item") -> Electronics | K12: =_xlfn.XLOOKUP(D12,Product_Master!A:A,Product_Master!D:D,"Unknown Item") -> 12.5 | L12: =_xlfn.XLOOKUP(D12,Product_Master!A:A,Product_Master!E:E,"Unknown Item") -> 39.99 | M12: =_xlfn.XLOOKUP(C12,Customer_database!A:A,Customer_database!E:E,"Unknown Customer") -> Creed Bratton | N12: =_xlfn.XLOOKUP(C12,Customer_database!A:A,Customer_database!D:D,"Unknown") -> Gold | O12: =E12*L12 -> 799.8 | P12: =(L12-K12)*E12 -> 549.8 | Q12: =F12-B12 -> 1 | R12: =IF(AND(Q12>5,OR(G12="North",G12="South")),"CRITICAL DELAY", IF(Q12>5,"Late","On Time")) -> On Time | S12: =OR(H12="WELCOME10",H12="FREESHIP") -> FALSE
A13: ORD-24-1012 | B13: 45316 | C13: C-007 | D13: P-502 | E13: 3 | F13: 45327 | G13: East | I13: =_xlfn.XLOOKUP(D13,Product_Master!A:A,Product_Master!B:B,"Unknown Item") -> Ergo Office Chair | J13: =_xlfn.XLOOKUP(D13,Product_Master!A:A,Product_Master!C:C,"Unknown Item") -> Furniture | K13: =_xlfn.XLOOKUP(D13,Product_Master!A:A,Product_Master!D:D,"Unknown Item") -> 85 | L13: =_xlfn.XLOOKUP(D13,Product_Master!A:A,Product_Master!E:E,"Unknown Item") -> 249.99 | M13: =_xlfn.XLOOKUP(C13,Customer_database!A:A,Customer_database!E:E,"Unknown Customer") -> Pam Beesly | N13: =_xlfn.XLOOKUP(C13,Customer_database!A:A,Customer_database!D:D,"Unknown") -> Silver | O13: =E13*L13 -> 749.97 | P13: =(L13-K13)*E13 -> 494.97 | Q13: =F13-B13 -> 11 | R13: =IF(AND(Q13>5,OR(G13="North",G13="South")),"CRITICAL DELAY", IF(Q13>5,"Late","On Time")) -> Late | S13: =OR(H13="WELCOME10",H13="FREESHIP") -> FALSE
A14: ORD-24-1013 | B14: 45317 | C14: C-010 | D14: P-503 | E14: 2 | F14: 45319 | G14: South | H14: WELCOME10 | I14: =_xlfn.XLOOKUP(D14,Product_Master!A:A,Product_Master!B:B,"Unknown Item") -> Oak Standing Desk | J14: =_xlfn.XLOOKUP(D14,Product_Master!A:A,Product_Master!C:C,"Unknown Item") -> Furniture | K14: =_xlfn.XLOOKUP(D14,Product_Master!A:A,Product_Master!D:D,"Unknown Item") -> 160 | L14: =_xlfn.XLOOKUP(D14,Product_Master!A:A,Product_Master!E:E,"Unknown Item") -> 450 | M14: =_xlfn.XLOOKUP(C14,Customer_database!A:A,Customer_database!E:E,"Unknown Customer") -> Stanley Hudson | N14: =_xlfn.XLOOKUP(C14,Customer_database!A:A,Customer_database!D:D,"Unknown") -> Silver | O14: =E14*L14 -> 900 | P14: =(L14-K14)*E14 -> 580 | Q14: =F14-B14 -> 2 | R14: =IF(AND(Q14>5,OR(G14="North",G14="South")),"CRITICAL DELAY", IF(Q14>5,"Late","On Time")) -> On Time | S14: =OR(H14="WELCOME10",H14="FREESHIP") -> TRUE
A15: ORD-24-1014 | B15: 45319 | C15: C-005 | D15: P-504 | E15: 1 | F15: 45324 | G15: North | I15: =_xlfn.XLOOKUP(D15,Product_Master!A:A,Product_Master!B:B,"Unknown Item") -> Smart LED Lamp | J15: =_xlfn.XLOOKUP(D15,Product_Master!A:A,Product_Master!C:C,"Unknown Item") -> Home Decor | K15: =_xlfn.XLOOKUP(D15,Product_Master!A:A,Product_Master!D:D,"Unknown Item") -> 15 | L15: =_xlfn.XLOOKUP(D15,Product_Master!A:A,Product_Master!E:E,"Unknown Item") -> 45 | M15: =_xlfn.XLOOKUP(C15,Customer_database!A:A,Customer_database!E:E,"Unknown Customer") -> Dwight Schrute | N15: =_xlfn.XLOOKUP(C15,Customer_database!A:A,Customer_database!D:D,"Unknown") -> Silver | O15: =E15*L15 -> 45 | P15: =(L15-K15)*E15 -> 30 | Q15: =F15-B15 -> 5 | R15: =IF(AND(Q15>5,OR(G15="North",G15="South")),"CRITICAL DELAY", IF(Q15>5,"Late","On Time")) -> On Time | S15: =OR(H15="WELCOME10",H15="FREESHIP") -> FALSE
A16: ORD-24-1015 | B16: 45321 | C16: C-001 | D16: P-501 | E16: 5 | F16: 45323 | G16: North | H16: FREESHIP | I16: =_xlfn.XLOOKUP(D16,Product_Master!A:A,Product_Master!B:B,"Unknown Item") -> Mech Keyboard RGB | J16: =_xlfn.XLOOKUP(D16,Product_Master!A:A,Product_Master!C:C,"Unknown Item") -> Electronics | K16: =_xlfn.XLOOKUP(D16,Product_Master!A:A,Product_Master!D:D,"Unknown Item") -> 45 | L16: =_xlfn.XLOOKUP(D16,Product_Master!A:A,Product_Master!E:E,"Unknown Item") -> 129.99 | M16: =_xlfn.XLOOKUP(C16,Customer_database!A:A,Customer_database!E:E,"Unknown Customer") -> John Smith | N16: =_xlfn.XLOOKUP(C16,Customer_database!A:A,Customer_database!D:D,"Unknown") -> Gold | O16: =E16*L16 -> 649.95 | P16: =(L16-K16)*E16 -> 424.95 | Q16: =F16-B16 -> 2 | R16: =IF(AND(Q16>5,OR(G16="North",G16="South")),"CRITICAL DELAY", IF(Q16>5,"Late","On Time")) -> On Time | S16: =OR(H16="WELCOME10",H16="FREESHIP") -> TRUE

Sheet Product_Master
A1: Prod_ID | B1: Product_Name | C1: Category | D1: Unit_Cost | E1: Unit_Price | F1: Supplier
A2: P-500 | B2: Wireless Mouse X1 | C2: Electronics | D2: 12.5 | E2: 39.99 | F2: TechGiant
A3: P-501 | B3: Mech Keyboard RGB | C3: Electronics | D3: 45 | E3: 129.99 | F3: KeyWorld
A4: P-502 | B4: Ergo Office Chair | C4: Furniture | D4: 85 | E4: 249.99 | F4: SitRight
A5: P-503 | B5: Oak Standing Desk | C5: Furniture | D5: 160 | E5: 450 | F5: WoodWorks
A6: P-504 | B6: Smart LED Lamp | C6: Home Decor | D6: 15 | E6: 45 | F6: BrightLite
A7: P-505 | B7: Dual Monitor Arm | C7: Electronics | D7: 25 | E7: 75 | F7: TechGiant
A8: P-999 | B8: Extended Warranty | C8: Services | D8: 5 | E8: 25 | F8: ApexLogistics

Sheet Customer_database
A1: Column1 | B1: Column2 | C1: Column3 | D1: Column4 | E1: Column5 | F1: Column6
A2: Cust_ID | B2: Customer_Raw_Name | C2: Email_Address | D2: Membership_Tier | E2: Clean Name | F2: Email Domain
A3: C-001 | B3: john smith | C3: j.smith@gmail.com | D3: Gold | E3: =PROPER(TRIM(B3)) -> John Smith | F3: =RIGHT(C3,LEN(C3)-FIND("@",C3)) -> gmail.com
A4: C-002 | B4: SARAH CONNOR | C4: s.connor@skynet.org | D4: Silver | E4: =PROPER(TRIM(B4)) -> Sarah Connor | F4: =RIGHT(C4,LEN(C4)-FIND("@",C4)) -> skynet.org
A5: C-003 | B5: emily blunt | C5: e.blunt@studio.net | D5: Bronze | E5: =PROPER(TRIM(B5)) -> Emily Blunt | F5: =RIGHT(C5,LEN(C5)-FIND("@",C5)) -> studio.net
A6: C-004 | B6: MICHAEL scott | C6: m.scott@paperco.com | D6: Gold | E6: =PROPER(TRIM(B6)) -> Michael Scott | F6: =RIGHT(C6,LEN(C6)-FIND("@",C6)) -> paperco.com
A7: C-005 | B7: dwight Schrute | C7: beets@farms.com | D7: Silver | E7: =PROPER(TRIM(B7)) -> Dwight Schrute | F7: =RIGHT(C7,LEN(C7)-FIND("@",C7)) -> farms.com
A8: C-006 | B8: jim HALPERT | C8: jim@paperco.com | D8: Bronze | E8: =PROPER(TRIM(B8)) -> Jim Halpert | F8: =RIGHT(C8,LEN(C8)-FIND("@",C8)) -> paperco.com
A9: C-007 | B9: pam beesly | C9: art@paperco.com | D9: Silver | E9: =PROPER(TRIM(B9)) -> Pam Beesly | F9: =RIGHT(C9,LEN(C9)-FIND("@",C9)) -> paperco.com
A10: C-008 | B10: ryan howard | C10: temp@agency.com | D10: Bronze | E10: =PROPER(TRIM(B10)) -> Ryan Howard | F10: =RIGHT(C10,LEN(C10)-FIND("@",C10)) -> agency.com
A11: C-009 | B11: Creed Bratton | C11: unknown@unknown.com | D11: Gold | E11: =PROPER(TRIM(B11)) -> Creed Bratton | F11: =RIGHT(C11,LEN(C11)-FIND("@",C11)) -> unknown.com
A12: C-010 | B12: stanley hudson | C12: crossword@paperco.com | D12: Silver | E12: =PROPER(TRIM(B12)) -> Stanley Hudson | F12: =RIGHT(C12,LEN(C12)-FIND("@",C12)) -> paperco.com
